[
  { "anonymous": false, "inputs": [
    { "indexed": true, "internalType": "address", "name": "from", "type": "address" },
    { "indexed": false, "internalType": "uint256", "name": "amount", "type": "uint256" }
  ], "name": "AdminDeposit", "type": "event" },
  { "anonymous": false, "inputs": [
    { "indexed": true, "internalType": "address", "name": "creator", "type": "address" },
    { "indexed": false, "internalType": "uint256", "name": "amount", "type": "uint256" }
  ], "name": "AdminWithdrawn", "type": "event" },
  { "anonymous": false, "inputs": [
    { "indexed": true, "internalType": "address", "name": "previousOwner", "type": "address" },
    { "indexed": true, "internalType": "address", "name": "newOwner", "type": "address" }
  ], "name": "OwnershipTransferred", "type": "event" },
  { "inputs": [], "name": "adminRevenue", "outputs": [{ "internalType": "uint256", "name": "", "type": "uint256" }], "stateMutability": "view", "type": "function" },
  { "inputs": [{ "internalType": "uint256", "name": "amount", "type": "uint256" }], "name": "depositAdmin", "outputs": [], "stateMutability": "payable", "type": "function" },
  { "inputs": [], "name": "owner", "outputs": [{ "internalType": "address", "name": "", "type": "address" }], "stateMutability": "view", "type": "function" },
  { "inputs": [], "name": "renounceOwnership", "outputs": [], "stateMutability": "nonpayable", "type": "function" },
  { "inputs": [{ "internalType": "address", "name": "newOwner", "type": "address" }], "name": "transferOwnership", "outputs": [], "stateMutability": "nonpayable", "type": "function" },
  { "inputs": [], "name": "withdraw", "outputs": [], "stateMutability": "nonpayable", "type": "function" }
] 